gbto/__init__.py
gbto/cli.py
gbto/enhanced_validator.py
gbto/execution.py
gbto/graph.py
gbto/nodes.py
gbto/static_validator.py
gbto/visualizer.py
graph_based_task_orchestrator-0.2.3.dist-info/METADATA
graph_based_task_orchestrator-0.2.3.dist-info/WHEEL
graph_based_task_orchestrator-0.2.3.dist-info/entry_points.txt
graph_based_task_orchestrator-0.2.3.dist-info/top_level.txt
graph_based_task_orchestrator-0.2.3.dist-info/RECORD
