Metadata-Version: 2.4
Name: graph-based-task-orchestrator
Version: 0.2.3
Summary: A simple yet powerful task orchestration library based on graph data structure
Requires-Python: >=3.13
Requires-Dist: pydantic>=2.0.0
Provides-Extra: dev
Requires-Dist: pytest>=7.4.0; extra == "dev"
Requires-Dist: black>=23.0.0; extra == "dev"
Requires-Dist: mypy>=1.5.0; extra == "dev"
